tensor_iroh-0.1.1a3.dist-info/METADATA
tensor_iroh-0.1.1a3.dist-info/WHEEL
tensor_iroh/__init__.py
tensor_iroh/tensor_iroh.abi3.so
tensor_iroh-0.1.1a3.dist-info/RECORD
