Metadata-Version: 2.4
Name: tensor_iroh
Version: 0.1.1a3
Classifier: Development Status :: 4 - Beta
Classifier: Intended Audience :: Developers
Classifier: License :: OSI Approved :: MIT License
Classifier: Programming Language :: Python :: 3
Classifier: Programming Language :: Python :: 3.8
Classifier: Programming Language :: Python :: 3.9
Classifier: Programming Language :: Python :: 3.10
Classifier: Programming Language :: Python :: 3.11
Classifier: Programming Language :: Python :: 3.12
Classifier: Programming Language :: Rust
Classifier: Topic :: Scientific/Engineering :: Artificial Intelligence
Requires-Dist: numpy>=1.21.0
Summary: High-performance PyO3 bindings for tensor_iroh
Keywords: tensor,p2p,iroh,machine-learning
License: MIT
Requires-Python: >=3.8
Project-URL: Homepage, https://github.com/Tandemn-Labs/tensor-iroh
Project-URL: Repository, https://github.com/Tandemn-Labs/tensor-iroh
